<?xml version="1.0" encoding="UTF-8"?>
<qes:espresso xmlns:xsi="http://www.w3.org/2001/XMLSchema-instance" xmlns:qes="http://www.quantum-espresso.org/ns/qes/qes-1.0" xsi:schemaLocation="http://www.quantum-espresso.org/ns/qes/qes-1.0 http://www.quantum-espresso.org/ns/qes/qes_230310.xsd" Units="Hartree atomic units">
<!-- All quantities are in Hartree atomic units unless otherwise specified -->
  <general_info>
    <xml_format NAME="QEXSD" VERSION="23.03.10">QEXSD_23.03.10</xml_format>
    <creator NAME="PWSCF" VERSION="7.3.1">XML file generated by PWSCF</creator>
    <created DATE="27May2024" TIME="21:30:32">This run was terminated on:  21:30:32  27 May 2024</created>
    <job>ecut_test</job>
  </general_info>
  <parallel_info>
    <nprocs>24</nprocs>
    <nthreads>1</nthreads>
    <ntasks>1</ntasks>
    <nbgrp>1</nbgrp>
    <npool>1</npool>
    <ndiag>24</ndiag>
  </parallel_info>
  <input>
    <control_variables>
      <title>ecut_test</title>
      <calculation>scf</calculation>
      <restart_mode>from_scratch</restart_mode>
      <prefix>pwscf</prefix>
      <pseudo_dir>/home/mehlhorn/pseudos/</pseudo_dir>
      <outdir>./</outdir>
      <stress>false</stress>
      <forces>false</forces>
      <wf_collect>true</wf_collect>
      <disk_io>low</disk_io>
      <max_seconds>10000000</max_seconds>
      <nstep>1</nstep>
      <etot_conv_thr>5.000000000000000E-007</etot_conv_thr>
      <forc_conv_thr>5.000000000000000E-006</forc_conv_thr>
      <press_conv_thr>5.000000000000000E-001</press_conv_thr>
      <verbosity>low</verbosity>
      <print_every>100000</print_every>
      <fcp>false</fcp>
      <rism>false</rism>
    </control_variables>
    <atomic_species ntyp="3">
      <species name="B">
        <mass>1.081100000000000E+001</mass>
        <pseudo_file>b_pbesol_v1.4.uspp.F.UPF</pseudo_file>
      </species>
      <species name="Ba">
        <mass>1.373270000000000E+002</mass>
        <pseudo_file>Ba.nc.z_10.oncvpsp4.dojo.v4-sp.upf</pseudo_file>
      </species>
      <species name="H">
        <mass>1.007940000000000E+000</mass>
        <pseudo_file>H_ONCV_PBEsol-1.0.upf</pseudo_file>
      </species>
    </atomic_species>
    <atomic_structure nat="22" alat="13.199283446241093" bravais_index="8">
      <atomic_positions>
        <atom name="Ba" index="1">6.599641723120547E+000  6.829857608253082E+000  4.582714256839989E+000</atom>
        <atom name="Ba" index="2">0.000000000000000E+000  0.000000000000000E+000  9.163229162732849E+000</atom>
        <atom name="B" index="3">8.326107997888881E+000  3.469567664992566E+000  1.832792455943045E-004</atom>
        <atom name="B" index="4">4.873175448352211E+000  1.019014755151360E+001  1.832792455943045E-004</atom>
        <atom name="B" index="5">1.726466274768335E+000  3.360289943260516E+000  4.581797860612018E+000</atom>
        <atom name="B" index="6">1.147281717147276E+001  1.029942527324565E+001  4.581797860612018E+000</atom>
        <atom name="H" index="7">6.047911675067668E+000  3.879359121487751E+000  2.382630192725958E-003</atom>
        <atom name="H" index="8">7.151371771173424E+000  9.780356095018414E+000  2.382630192725958E-003</atom>
        <atom name="H" index="9">1.264755339818822E+001  2.950498486765332E+000  4.579598509664887E+000</atom>
        <atom name="H" index="10">5.517300480528776E-001  1.070921672974083E+001  4.579598509664887E+000</atom>
        <atom name="H" index="11">9.508763794672085E+000  5.466618029645767E+000  0.000000000000000E+000</atom>
        <atom name="H" index="12">3.690519651569010E+000  8.193097186860397E+000  0.000000000000000E+000</atom>
        <atom name="H" index="13">2.909122071551537E+000  1.363239578607315E+000  4.581981139857612E+000</atom>
        <atom name="H" index="14">1.029016137468956E+001  1.229647563789885E+001  4.581981139857612E+000</atom>
        <atom name="H" index="15">8.829000697190668E+000  2.262048839853421E+000  7.251809910429848E+000</atom>
        <atom name="H" index="16">4.370282749050426E+000  1.139766637665274E+001  7.251809910429848E+000</atom>
        <atom name="H" index="17">2.229358974070121E+000  4.567808768399661E+000  6.494133509142991E+000</atom>
        <atom name="H" index="18">1.096992447217097E+001  9.091906448106503E+000  6.494133509142991E+000</atom>
        <atom name="H" index="19">4.370282749050426E+000  1.139766637665274E+001  1.912152369285379E+000</atom>
        <atom name="H" index="20">8.829000697190668E+000  2.262048839853421E+000  1.912152369285379E+000</atom>
        <atom name="H" index="21">1.096992447217097E+001  9.091906448106503E+000  2.669828770572234E+000</atom>
        <atom name="H" index="22">2.229358974070121E+000  4.567808768399661E+000  2.669828770572234E+000</atom>
      </atomic_positions>
      <cell>
        <a1>1.319928344624109E+001  0.000000000000000E+000  0.000000000000000E+000</a1>
        <a2>0.000000000000000E+000  1.365971521650616E+001  0.000000000000000E+000</a2>
        <a3>0.000000000000000E+000  0.000000000000000E+000  9.163962279715225E+000</a3>
      </cell>
    </atomic_structure>
    <dft>
      <functional>PBESOL</functional>
    </dft>
    <spin>
      <lsda>false</lsda>
      <noncolin>false</noncolin>
      <spinorbit>false</spinorbit>
    </spin>
    <bands>
      <tot_charge>0.000000000000000E+000</tot_charge>
      <occupations>fixed</occupations>
    </bands>
    <basis>
      <gamma_only>true</gamma_only>
      <ecutwfc>5.000000000000000E+001</ecutwfc>
      <ecutrho>2.000000000000000E+002</ecutrho>
    </basis>
    <electron_control>
      <diagonalization>davidson</diagonalization>
      <mixing_mode>plain</mixing_mode>
      <mixing_beta>7.000000000000000E-001</mixing_beta>
      <conv_thr>5.000000000000000E-009</conv_thr>
      <mixing_ndim>8</mixing_ndim>
      <max_nstep>100</max_nstep>
      <exx_nstep>100</exx_nstep>
      <real_space_q>false</real_space_q>
      <real_space_beta>false</real_space_beta>
      <tq_smoothing>false</tq_smoothing>
      <tbeta_smoothing>false</tbeta_smoothing>
      <diago_thr_init>0.000000000000000E+000</diago_thr_init>
      <diago_full_acc>false</diago_full_acc>
      <diago_cg_maxiter>20</diago_cg_maxiter>
      <diago_ppcg_maxiter>20</diago_ppcg_maxiter>
      <diago_rmm_ndim>4</diago_rmm_ndim>
      <diago_gs_nblock>16</diago_gs_nblock>
      <diago_rmm_conv>false</diago_rmm_conv>
    </electron_control>
    <k_points_IBZ>
      <nk>1</nk>
      <k_point weight="1.0000000000000000">0.000000000000000E+000  0.000000000000000E+000  0.000000000000000E+000</k_point>
    </k_points_IBZ>
    <ion_control>
      <ion_dynamics>none</ion_dynamics>
      <upscale>1.000000000000000E+002</upscale>
      <remove_rigid_rot>false</remove_rigid_rot>
      <refold_pos>false</refold_pos>
    </ion_control>
    <cell_control>
      <cell_dynamics>none</cell_dynamics>
      <pressure>0.000000000000000E+000</pressure>
      <wmass>0.000000000000000E+000</wmass>
      <cell_do_free>all</cell_do_free>
    </cell_control>
    <symmetry_flags>
      <nosym>false</nosym>
      <nosym_evc>false</nosym_evc>
      <noinv>false</noinv>
      <no_t_rev>false</no_t_rev>
      <force_symmorphic>false</force_symmorphic>
      <use_all_frac>false</use_all_frac>
    </symmetry_flags>
  </input>
  <output>
    <convergence_info>
      <scf_conv>
        <convergence_achieved>true</convergence_achieved>
        <n_scf_steps>10</n_scf_steps>
        <scf_error>1.336853302246629E-009</scf_error>
      </scf_conv>
    </convergence_info>
    <algorithmic_info>
      <real_space_q>false</real_space_q>
      <real_space_beta>false</real_space_beta>
      <uspp>true</uspp>
      <paw>false</paw>
    </algorithmic_info>
    <atomic_species ntyp="3" pseudo_dir="/home/mehlhorn/pseudos/">
      <species name="B">
        <mass>1.081100000000000E+001</mass>
        <pseudo_file>b_pbesol_v1.4.uspp.F.UPF</pseudo_file>
      </species>
      <species name="Ba">
        <mass>1.373270000000000E+002</mass>
        <pseudo_file>Ba.nc.z_10.oncvpsp4.dojo.v4-sp.upf</pseudo_file>
      </species>
      <species name="H">
        <mass>1.007940000000000E+000</mass>
        <pseudo_file>H_ONCV_PBEsol-1.0.upf</pseudo_file>
      </species>
    </atomic_species>
    <atomic_structure nat="22" alat="13.199283446241093" bravais_index="8">
      <atomic_positions>
        <atom name="Ba" index="1">6.599641723120547E+000  6.829857608253082E+000  4.582714256839989E+000</atom>
        <atom name="Ba" index="2">0.000000000000000E+000  0.000000000000000E+000  9.163229162732849E+000</atom>
        <atom name="B" index="3">8.326107997888881E+000  3.469567664992566E+000  1.832792455943045E-004</atom>
        <atom name="B" index="4">4.873175448352211E+000  1.019014755151360E+001  1.832792455943045E-004</atom>
        <atom name="B" index="5">1.726466274768335E+000  3.360289943260516E+000  4.581797860612018E+000</atom>
        <atom name="B" index="6">1.147281717147276E+001  1.029942527324565E+001  4.581797860612018E+000</atom>
        <atom name="H" index="7">6.047911675067668E+000  3.879359121487751E+000  2.382630192725958E-003</atom>
        <atom name="H" index="8">7.151371771173424E+000  9.780356095018414E+000  2.382630192725958E-003</atom>
        <atom name="H" index="9">1.264755339818822E+001  2.950498486765332E+000  4.579598509664887E+000</atom>
        <atom name="H" index="10">5.517300480528776E-001  1.070921672974083E+001  4.579598509664887E+000</atom>
        <atom name="H" index="11">9.508763794672085E+000  5.466618029645767E+000  0.000000000000000E+000</atom>
        <atom name="H" index="12">3.690519651569010E+000  8.193097186860397E+000  0.000000000000000E+000</atom>
        <atom name="H" index="13">2.909122071551537E+000  1.363239578607315E+000  4.581981139857612E+000</atom>
        <atom name="H" index="14">1.029016137468956E+001  1.229647563789885E+001  4.581981139857612E+000</atom>
        <atom name="H" index="15">8.829000697190668E+000  2.262048839853421E+000  7.251809910429848E+000</atom>
        <atom name="H" index="16">4.370282749050426E+000  1.139766637665274E+001  7.251809910429848E+000</atom>
        <atom name="H" index="17">2.229358974070121E+000  4.567808768399661E+000  6.494133509142991E+000</atom>
        <atom name="H" index="18">1.096992447217097E+001  9.091906448106503E+000  6.494133509142991E+000</atom>
        <atom name="H" index="19">4.370282749050426E+000  1.139766637665274E+001  1.912152369285379E+000</atom>
        <atom name="H" index="20">8.829000697190668E+000  2.262048839853421E+000  1.912152369285379E+000</atom>
        <atom name="H" index="21">1.096992447217097E+001  9.091906448106503E+000  2.669828770572234E+000</atom>
        <atom name="H" index="22">2.229358974070121E+000  4.567808768399661E+000  2.669828770572234E+000</atom>
      </atomic_positions>
      <cell>
        <a1>1.319928344624109E+001  0.000000000000000E+000  0.000000000000000E+000</a1>
        <a2>0.000000000000000E+000  1.365971521650616E+001  0.000000000000000E+000</a2>
        <a3>0.000000000000000E+000  0.000000000000000E+000  9.163962279715225E+000</a3>
      </cell>
    </atomic_structure>
    <symmetries>
      <nsym>4</nsym>
      <nrot>8</nrot>
      <space_group>0</space_group>
      <symmetry>
        <info name="identity">crystal_symmetry</info>
        <rotation rank="2" dims="           3           3">
  1.000000000000000E+000  0.000000000000000E+000  0.000000000000000E+000
  0.000000000000000E+000  1.000000000000000E+000  0.000000000000000E+000
  0.000000000000000E+000  0.000000000000000E+000  1.000000000000000E+000
        </rotation>
        <fractional_translation>
  0.000000000000000E+000  0.000000000000000E+000  0.000000000000000E+000
        </fractional_translation>
        <equivalent_atoms size="22" nat="22">
           1           2           3           4           5           6
           7           8
           9          10          11          12          13          14
          15          16
          17          18          19          20          21          22
        </equivalent_atoms>
      </symmetry>
      <symmetry>
        <info name="180 deg rotation - cart. axis [0,0,1]">crystal_symmetry</info>
        <rotation rank="2" dims="           3           3">
 -1.000000000000000E+000  0.000000000000000E+000  0.000000000000000E+000
  0.000000000000000E+000 -1.000000000000000E+000  0.000000000000000E+000
  0.000000000000000E+000  0.000000000000000E+000  1.000000000000000E+000
        </rotation>
        <fractional_translation>
  0.000000000000000E+000  0.000000000000000E+000  0.000000000000000E+000
        </fractional_translation>
        <equivalent_atoms size="22" nat="22">
           1           2           4           3           6           5
           8           7
          10           9          12          11          14          13
          16          15
          18          17          20          19          22          21
        </equivalent_atoms>
      </symmetry>
      <symmetry>
        <info name="180 deg rotation - cart. axis [0,1,0]">crystal_symmetry</info>
        <rotation rank="2" dims="           3           3">
 -1.000000000000000E+000  0.000000000000000E+000  0.000000000000000E+000
  0.000000000000000E+000  1.000000000000000E+000  0.000000000000000E+000
  0.000000000000000E+000  0.000000000000000E+000 -1.000000000000000E+000
        </rotation>
        <fractional_translation>
  5.000000000000000E-001  5.000000000000000E-001  5.000000000000000E-001
        </fractional_translation>
        <equivalent_atoms size="22" nat="22">
           2           1           6           5           4           3
          10           9
           8           7          14          13          12          11
          18          17
          16          15          22          21          20          19
        </equivalent_atoms>
      </symmetry>
      <symmetry>
        <info name="180 deg rotation - cart. axis [1,0,0]">crystal_symmetry</info>
        <rotation rank="2" dims="           3           3">
  1.000000000000000E+000  0.000000000000000E+000  0.000000000000000E+000
  0.000000000000000E+000 -1.000000000000000E+000  0.000000000000000E+000
  0.000000000000000E+000  0.000000000000000E+000 -1.000000000000000E+000
        </rotation>
        <fractional_translation>
  5.000000000000000E-001  5.000000000000000E-001  5.000000000000000E-001
        </fractional_translation>
        <equivalent_atoms size="22" nat="22">
           2           1           5           6           3           4
           9          10
           7           8          13          14          11          12
          17          18
          15          16          21          22          19          20
        </equivalent_atoms>
      </symmetry>
      <symmetry>
        <info name="inversion">lattice_symmetry</info>
        <rotation rank="2" dims="           3           3">
 -1.000000000000000E+000  0.000000000000000E+000  0.000000000000000E+000
  0.000000000000000E+000 -1.000000000000000E+000  0.000000000000000E+000
  0.000000000000000E+000  0.000000000000000E+000 -1.000000000000000E+000
        </rotation>
      </symmetry>
      <symmetry>
        <info name="inv. 180 deg rotation - cart. axis [0,0,1]">lattice_symmetry</info>
        <rotation rank="2" dims="           3           3">
  1.000000000000000E+000  0.000000000000000E+000  0.000000000000000E+000
  0.000000000000000E+000  1.000000000000000E+000  0.000000000000000E+000
  0.000000000000000E+000  0.000000000000000E+000 -1.000000000000000E+000
        </rotation>
      </symmetry>
      <symmetry>
        <info name="inv. 180 deg rotation - cart. axis [0,1,0]">lattice_symmetry</info>
        <rotation rank="2" dims="           3           3">
  1.000000000000000E+000  0.000000000000000E+000  0.000000000000000E+000
  0.000000000000000E+000 -1.000000000000000E+000  0.000000000000000E+000
  0.000000000000000E+000  0.000000000000000E+000  1.000000000000000E+000
        </rotation>
      </symmetry>
      <symmetry>
        <info name="inv. 180 deg rotation - cart. axis [1,0,0]">lattice_symmetry</info>
        <rotation rank="2" dims="           3           3">
 -1.000000000000000E+000  0.000000000000000E+000  0.000000000000000E+000
  0.000000000000000E+000  1.000000000000000E+000  0.000000000000000E+000
  0.000000000000000E+000  0.000000000000000E+000  1.000000000000000E+000
        </rotation>
      </symmetry>
    </symmetries>
    <basis_set>
      <gamma_only>true</gamma_only>
      <ecutwfc>5.000000000000000E+001</ecutwfc>
      <ecutrho>2.000000000000000E+002</ecutrho>
      <fft_grid nr1="90" nr2="90" nr3="60"></fft_grid>
      <fft_smooth nr1="90" nr2="90" nr3="60"></fft_smooth>
      <fft_box nr1="90" nr2="90" nr3="60"></fft_box>
      <ngm>111575</ngm>
      <ngms>111575</ngms>
      <npwx>13969</npwx>
      <reciprocal_lattice>
        <b1>
  1.000000000000000E+000  0.000000000000000E+000  0.000000000000000E+000
        </b1>
        <b2>0.000000000000000E+000  9.662927255094826E-001  0.000000000000000E+000</b2>
        <b3>0.000000000000000E+000  0.000000000000000E+000  1.440346767408483E+000</b3>
      </reciprocal_lattice>
    </basis_set>
    <dft>
      <functional>PBESOL</functional>
    </dft>
    <magnetization>
      <lsda>false</lsda>
      <noncolin>false</noncolin>
      <spinorbit>false</spinorbit>
      <absolute>0.000000000000000E+000</absolute>
    </magnetization>
    <total_energy>
      <etot>-7.820141493420290E+001</etot>
      <eband>-1.076482461451901E+001</eband>
      <ehart>1.524050758198096E+001</ehart>
      <vtxc>-2.341616148667216E+001</vtxc>
      <etxc>-2.450858806265778E+001</etxc>
      <ewald>-5.110358163174413E+001</ewald>
    </total_energy>
    <band_structure>
      <lsda>false</lsda>
      <noncolin>false</noncolin>
      <spinorbit>false</spinorbit>
      <nbnd>24</nbnd>
      <nelec>4.800000000000000E+001</nelec>
      <num_of_atomic_wfc>42</num_of_atomic_wfc>
      <wf_collected>true</wf_collected>
      <fermi_energy>-3.104284910982994E-003</fermi_energy>
      <highestOccupiedLevel>-3.104284910982994E-003</highestOccupiedLevel>
      <starting_k_points>
        <nk>1</nk>
        <k_point weight="1.0000000000000000">0.000000000000000E+000  0.000000000000000E+000  0.000000000000000E+000</k_point>
      </starting_k_points>
      <nks>1</nks>
      <occupations_kind>fixed</occupations_kind>
      <ks_energies>
        <k_point weight="2.0000000000000000">0.000000000000000E+000  0.000000000000000E+000  0.000000000000000E+000</k_point>
        <npw>13969</npw>
        <eigenvalues size="24">
 -9.267719814913902E-001 -9.266150378492093E-001 -3.887047149687628E-001
 -3.873107340024582E-001 -3.824948757730568E-001
 -3.819916432168912E-001 -3.792354490546667E-001 -3.777535448759528E-001
 -2.415856475397805E-001 -2.128380657232732E-001
 -2.002577234637468E-001 -1.954224627038994E-001 -8.148340881683569E-002
 -5.083610820333699E-002 -4.951180136426611E-002
 -3.754858037365694E-002 -3.557240956897840E-002 -3.360366242875977E-002
 -3.072569967983953E-002 -2.998969570836316E-002
 -1.866054615220007E-002 -5.200923658017618E-003 -5.193305731180454E-003
 -3.104284910982994E-003
        </eigenvalues>
        <occupations size="24">
  1.000000000000000E+000  1.000000000000000E+000  1.000000000000000E+000
  1.000000000000000E+000  1.000000000000000E+000
  1.000000000000000E+000  1.000000000000000E+000  1.000000000000000E+000
  1.000000000000000E+000  1.000000000000000E+000
  1.000000000000000E+000  1.000000000000000E+000  1.000000000000000E+000
  1.000000000000000E+000  1.000000000000000E+000
  1.000000000000000E+000  1.000000000000000E+000  1.000000000000000E+000
  1.000000000000000E+000  1.000000000000000E+000
  1.000000000000000E+000  1.000000000000000E+000  1.000000000000000E+000
  1.000000000000000E+000
        </occupations>
      </ks_energies>
    </band_structure>
  </output>
  <exit_status>0</exit_status>
  <timing_info>
    <total label="PWSCF">
      <cpu>3.625620000000000E+000</cpu>
      <wall>4.600293874740601E+000</wall>
    </total>
    <partial label="init_run" calls="1">
      <cpu>5.182279999999999E-001</cpu>
      <wall>1.330211162567139E+000</wall>
    </partial>
    <partial label="hinit0" calls="1">
      <cpu>3.240510000000000E-001</cpu>
      <wall>1.117923974990845E+000</wall>
    </partial>
    <partial label="init_vloc" calls="1">
      <cpu>2.230900000000002E-002</cpu>
      <wall>2.257013320922852E-002</wall>
    </partial>
    <partial label="init_us_1" calls="1">
      <cpu>4.290900000000003E-002</cpu>
      <wall>6.297588348388672E-002</wall>
    </partial>
    <partial label="fft" calls="99">
      <cpu>3.851690000000025E-001</cpu>
      <wall>1.191662788391113E+000</wall>
    </partial>
    <partial label="fft_scatter" calls="1049">
      <cpu>3.600540000000012E-001</cpu>
      <wall>3.989379405975342E-001</wall>
    </partial>
    <partial label="potinit" calls="1">
      <cpu>4.780200000000001E-002</cpu>
      <wall>5.358600616455078E-002</wall>
    </partial>
    <partial label="v_of_rho" calls="11">
      <cpu>3.363499999999999E-001</cpu>
      <wall>3.710348606109619E-001</wall>
    </partial>
    <partial label="v_xc" calls="11">
      <cpu>3.097810000000001E-001</cpu>
      <wall>3.371407985687256E-001</wall>
    </partial>
    <partial label="v_h" calls="11">
      <cpu>2.642100000000003E-002</cpu>
      <wall>3.374886512756348E-002</wall>
    </partial>
    <partial label="newd" calls="11">
      <cpu>2.724780000000000E-001</cpu>
      <wall>2.907328605651855E-001</wall>
    </partial>
    <partial label="wfcinit" calls="1">
      <cpu>8.637300000000003E-002</cpu>
      <wall>9.194779396057129E-002</wall>
    </partial>
    <partial label="init_us_2" calls="21">
      <cpu>3.689899999999957E-002</cpu>
      <wall>4.385638236999512E-002</wall>
    </partial>
    <partial label="wfcinit:atom" calls="1">
      <cpu>6.350000000000522E-004</cpu>
      <wall>6.339550018310547E-004</wall>
    </partial>
    <partial label="atomic_wfc" calls="1">
      <cpu>6.240000000000689E-004</cpu>
      <wall>6.301403045654297E-004</wall>
    </partial>
    <partial label="wfcinit:wfcr" calls="1">
      <cpu>8.138100000000004E-002</cpu>
      <wall>8.561778068542480E-002</wall>
    </partial>
    <partial label="wfcrot" calls="1">
      <cpu>8.137600000000000E-002</cpu>
      <wall>8.561110496520996E-002</wall>
    </partial>
    <partial label="rotwfcg" calls="1">
      <cpu>8.136299999999996E-002</cpu>
      <wall>8.558607101440430E-002</wall>
    </partial>
    <partial label="rotwfcg:hpsi" calls="1">
      <cpu>5.903799999999992E-002</cpu>
      <wall>6.326007843017578E-002</wall>
    </partial>
    <partial label="h_psi_bgrp" calls="46">
      <cpu>1.229607000000000E+000</cpu>
      <wall>1.241577863693237E+000</wall>
    </partial>
    <partial label="h_psi" calls="46">
      <cpu>1.229144999999999E+000</cpu>
      <wall>1.241256237030029E+000</wall>
    </partial>
    <partial label="h_psi:pot" calls="46">
      <cpu>1.225277999999997E+000</cpu>
      <wall>1.236853122711182E+000</wall>
    </partial>
    <partial label="vloc_psi" calls="46">
      <cpu>7.481070000000001E-001</cpu>
      <wall>7.596702575683594E-001</wall>
    </partial>
    <partial label="fftw" calls="940">
      <cpu>7.584110000000046E-001</cpu>
      <wall>7.717375755310059E-001</wall>
    </partial>
    <partial label="h_psi:calbec" calls="46">
      <cpu>2.624989999999996E-001</cpu>
      <wall>2.626011371612549E-001</wall>
    </partial>
    <partial label="calbec" calls="56">
      <cpu>3.373560000000007E-001</cpu>
      <wall>3.377511501312256E-001</wall>
    </partial>
    <partial label="add_vuspsi" calls="46">
      <cpu>2.135829999999999E-001</cpu>
      <wall>2.137622833251953E-001</wall>
    </partial>
    <partial label="rotwfcg:hc" calls="1">
      <cpu>1.896299999999995E-002</cpu>
      <wall>1.897001266479492E-002</wall>
    </partial>
    <partial label="s_psi_bgrp" calls="46">
      <cpu>2.223230000000003E-001</cpu>
      <wall>2.223622798919678E-001</wall>
    </partial>
    <partial label="s_psi" calls="46">
      <cpu>2.161609999999996E-001</cpu>
      <wall>2.163288593292236E-001</wall>
    </partial>
    <partial label="rotwfcg:diag" calls="1">
      <cpu>1.529000000000003E-003</cpu>
      <wall>1.528024673461914E-003</wall>
    </partial>
    <partial label="rdiaghg" calls="45">
      <cpu>5.335299999999954E-002</cpu>
      <wall>5.689215660095215E-002</wall>
    </partial>
    <partial label="rotwfcg:evc" calls="1">
      <cpu>1.812000000000036E-003</cpu>
      <wall>1.814126968383789E-003</wall>
    </partial>
    <partial label="electrons" calls="1">
      <cpu>2.876414000000000E+000</cpu>
      <wall>3.011562108993530E+000</wall>
    </partial>
    <partial label="c_bands" calls="10">
      <cpu>1.821202000000000E+000</cpu>
      <wall>1.857703924179077E+000</wall>
    </partial>
    <partial label="regterg" calls="10">
      <cpu>1.746381000000000E+000</cpu>
      <wall>1.768125057220459E+000</wall>
    </partial>
    <partial label="regterg:init" calls="10">
      <cpu>2.631000000000006E-002</cpu>
      <wall>2.928113937377930E-002</wall>
    </partial>
    <partial label="regterg:upda" calls="35">
      <cpu>4.290399999999917E-002</cpu>
      <wall>4.385471343994141E-002</wall>
    </partial>
    <partial label="g_psi" calls="35">
      <cpu>5.408999999999331E-003</cpu>
      <wall>5.518674850463867E-003</wall>
    </partial>
    <partial label="regterg:over" calls="35">
      <cpu>1.078209999999995E-001</cpu>
      <wall>1.107048988342285E-001</wall>
    </partial>
    <partial label="regterg:diag" calls="44">
      <cpu>5.214099999999977E-002</cpu>
      <wall>5.564355850219727E-002</wall>
    </partial>
    <partial label="regterg:last" calls="27">
      <cpu>1.099359999999985E-001</cpu>
      <wall>1.115567684173584E-001</wall>
    </partial>
    <partial label="sum_band" calls="10">
      <cpu>4.379830000000013E-001</cpu>
      <wall>4.657828807830811E-001</wall>
    </partial>
    <partial label="sum_band:wei" calls="10">
      <cpu>1.489999999995106E-004</cpu>
      <wall>1.313686370849609E-004</wall>
    </partial>
    <partial label="sum_band:loo" calls="10">
      <cpu>2.045300000000001E-001</cpu>
      <wall>2.118873596191406E-001</wall>
    </partial>
    <partial label="sum_band:buf" calls="10">
      <cpu>1.499999999987622E-005</cpu>
      <wall>1.978874206542969E-005</wall>
    </partial>
    <partial label="sum_band:ini" calls="10">
      <cpu>1.806899999999967E-002</cpu>
      <wall>2.007079124450684E-002</wall>
    </partial>
    <partial label="sum_band:cal" calls="10">
      <cpu>7.574899999999962E-002</cpu>
      <wall>7.576465606689453E-002</wall>
    </partial>
    <partial label="sum_band:bec" calls="10">
      <cpu>2.889999999999837E-004</cpu>
      <wall>2.803802490234375E-004</wall>
    </partial>
    <partial label="ffts" calls="10">
      <cpu>1.796100000000012E-002</cpu>
      <wall>2.252459526062012E-002</wall>
    </partial>
    <partial label="addusdens" calls="10">
      <cpu>1.860160000000000E-001</cpu>
      <wall>1.986129283905029E-001</wall>
    </partial>
    <partial label="addusd:skk" calls="10">
      <cpu>2.733999999999792E-003</cpu>
      <wall>3.060340881347656E-003</wall>
    </partial>
    <partial label="sum_band:sym" calls="10">
      <cpu>2.371999999999952E-002</cpu>
      <wall>2.626490592956543E-002</wall>
    </partial>
    <partial label="mix_rho" calls="10">
      <cpu>4.617100000000063E-002</cpu>
      <wall>5.351448059082031E-002</wall>
    </partial>
    <partial label="high_freq_mi" calls="9">
      <cpu>1.557000000000031E-003</cpu>
      <wall>1.538991928100586E-003</wall>
    </partial>
    <partial label="ions" calls="1">
      <cpu>1.999999999835467E-006</cpu>
      <wall>9.536743164062500E-007</wall>
    </partial>
  </timing_info>
  <closed DATE="27 May 2024" TIME="21:30:32"></closed>
</qes:espresso>
